[{"status": ["Required"], "names": ["LOOK!:FUNDAMENTALS OF ART HISTORY, Author: DALLEVA, Publisher: PEARSON, Edition: 3RD 10, Price: 54.00 USD"], "isbns": ["9780205768714"], "title": "34013"}, {"status": ["Required", "Required"], "names": ["MAKING HISPANICS, Author: MORA, Publisher: UCP, Edition: 14, Price: 27.50 USD", "TROUBLE WITH UNITY, Author: BELTRAN, Publisher: OXF, Edition: 10, Price: 26.95 USD"], "isbns": ["9780226033839", "9780195375916"], "title": "34196"}, {"status": ["Required", "Required"], "names": ["READINGS IN LATIN AMERICAN MODERN ART, Author: FRANK, Publisher: TRILITERAL, Edition: 04, Price: 30.00 USD", "TWENTIETH-CENTURY ART OF LATIN AMERICA, Author: BARNITZ, Publisher: U OF TX, Edition: REV 15, Price: 58.65 USD"], "isbns": ["9780300102550", "9781477308042"], "title": "37292"}, {"status": ["Required", "Required", "Required", "Required"], "names": ["BREATH,EYES,MEMORY, Author: DANTICAT, Publisher: PENG RAND, Edition: 94, Price: 15.00 USD", "ENRIQUE'S JOURNEY-REV.+UPDT.(W/359 PGS), Author: NAZARIO, Publisher: PENG RAND, Edition: 06, Price: 16.00 USD", "IN SEARCH OF BERNABE, Author: LIMON, Publisher: ARTE PUB, Edition: 93, Price: 10.95 USD", "LATINA/CHICANA MOTHERING, Author: SILVA, Publisher: BRUNSWICK, Edition: 11, Price: 34.95 USD"], "isbns": ["9780375705045", "9780812971781", "9781558850736", "9780986667138"], "title": "36921"}, {"status": [], "names": [], "isbns": [], "title": "34015"}, {"status": [], "names": [], "isbns": [], "title": "34016"}, {"status": ["Required"], "names": ["TEACHING TO TRANSGRESS, Author: HOOKS, Publisher: TAYLOR, Edition: 94, Price: 36.95 USD"], "isbns": ["9780415908085"], "title": "37060"}, {"status": [], "names": [], "isbns": [], "title": "37460"}, {"status": ["Required", "Required", "Required", "Required", "Required", "Required"], "names": ["ANTONIO GRAMSCI READER, Author: GRAMSCI, Publisher: NYU, Edition: 99, Price: 27.00 USD", "PEASANT WARS OF TWENTIETH CENTURY, Author: WOLF, Publisher: U OF OK, Edition: 99, Price: 24.95 USD", "REVOLUTIONARY IRAN, Author: AXWORTHY, Publisher: OXF, Edition: 13, Price: 34.95 USD", "REVOLUTIONARY MEXICO-TENTH ANNIV.ED., Author: HART, Publisher: PERSEUS D, Edition: (REV)97, Price: 34.95 USD", "REVOLUTIONS:THEORETICAL,COMP...STUDIES, Author: GOLDSTONE, Publisher: CENGAGE L, Edition: 3RD 03, Price: 166.35 USD", "STATES+SOCIAL REVOLUTIONS, Author: SKOCPOL, Publisher: CAMB, Edition: 15, Price: 20.00 USD"], "isbns": ["9780814727010", "9780806131962", "9780199322268", "9780520215313", "9780155066793", "9781107569843"], "title": "37116"}, {"status": [], "names": [], "isbns": [], "title": "34017"}]