[{"status": [], "names": [], "isbns": [], "title": "30946"}, {"status": [], "names": [], "isbns": [], "title": "30947"}, {"status": ["Required", "Required", "Required", "Required", "Required", "Ebook Option"], "names": ["BIG WHITE FOG, Author: WARD, Publisher: PERSEUS D, Edition: 08, Price: 20.95 USD", "BLACK THEATER USA:...1935-TODAY,REV+EXP, Author: HATCH, Publisher: S+S, Edition: REV 96, Price: 27.00 USD", "CHOIR BOY, Author: MCCRANEY, Publisher: PERSEUS D, Edition: 16, Price: 14.95 USD", "GROUND ON WHICH I STAND, Author: WILSON, Publisher: PERSEUS D, Edition: 01, Price: 9.95 USD", "TOPDOG/UNDERDOG, Author: PARKS, Publisher: PERSEUS D, Edition: 01, Price: 14.95 USD", "EBK TOPDOG/UNDERDOG, Author: PARKS, Publisher: DGTL BNCOM, Price: 14.95 USD"], "isbns": ["9781854595959", "9780684823072", "9781559364683", "9781559361873", "9781559362016", "9781559366243"], "title": "37693"}, {"status": [], "names": [], "isbns": [], "title": "30945"}, {"status": [], "names": [], "isbns": [], "title": "30948"}]