[{"status": [], "names": [], "isbns": [], "title": "22331"}, {"status": [], "names": [], "isbns": [], "title": "23087"}, {"status": [], "names": [], "isbns": [], "title": "22332"}, {"status": [], "names": [], "isbns": [], "title": "23088"}, {"status": [], "names": [], "isbns": [], "title": "22333"}, {"status": [], "names": [], "isbns": [], "title": "22334"}, {"status": ["Recommended", "Recommended", "Go to Class First"], "names": ["BOOTSTRAPPER'S GUIDE TO THE MOBILE WEB, Author: HAY, Publisher: LINDEN PUB, Edition: 12, Price: 24.95 USD", "MOBILE DESIGN+DEVELOPMENT, Author: FLING, Publisher: INGRAM PUB, Edition: 09, Price: 35.00 USD", "XAMARIN MOBILE APPLICATION DEVELOPMENT, Author: REYNOLDS, Publisher: PACKT PUB, Edition: 14, Price: 46.65 USD"], "isbns": ["9781610350525", "9780596155445", "9781783559169"], "title": "22338"}, {"status": ["Recommended", "Recommended", "Go to Class First"], "names": ["BOOTSTRAPPER'S GUIDE TO THE MOBILE WEB, Author: HAY, Publisher: LINDEN PUB, Edition: 12, Price: 24.95 USD", "MOBILE DESIGN+DEVELOPMENT, Author: FLING, Publisher: INGRAM PUB, Edition: 09, Price: 35.00 USD", "XAMARIN MOBILE APPLICATION DEVELOPMENT, Author: REYNOLDS, Publisher: PACKT PUB, Edition: 14, Price: 46.65 USD"], "isbns": ["9781610350525", "9780596155445", "9781783559169"], "title": "22339"}]