[{"status": ["Required", "Ebook Option", "Ebook Option"], "names": ["ESSENTIALS OF SYSTEMS ANALYSIS+DESIGN, Author: VALACICH, Publisher: PEARSON, Edition: 6TH 15, Price: 241.80 USD", "EBK ESSENTIALS OF SYSTEMS ANALYSIS AND, Author: VALACICH, Publisher: DGTL BNCOM, Edition: 6, Price: 98.99 USD", "EBK ESSENTIALS OF SYSTEMS ANALYSIS AND, Author: VALACICH, Publisher: DGTL BNCOM, Edition: 6, Price: 144.99 USD"], "isbns": ["9780133546231", "8220020246093", "9780133546361"], "title": "22502"}, {"status": ["Required", "Ebook Option", "Ebook Option"], "names": ["ESSENTIALS OF SYSTEMS ANALYSIS+DESIGN, Author: VALACICH, Publisher: PEARSON, Edition: 6TH 15, Price: 241.80 USD", "EBK ESSENTIALS OF SYSTEMS ANALYSIS AND, Author: VALACICH, Publisher: DGTL BNCOM, Edition: 6, Price: 98.99 USD", "EBK ESSENTIALS OF SYSTEMS ANALYSIS AND, Author: VALACICH, Publisher: DGTL BNCOM, Edition: 6, Price: 144.99 USD"], "isbns": ["9780133546231", "8220020246093", "9780133546361"], "title": "26731"}, {"status": ["Required", "Ebook Option", "Ebook Option"], "names": ["ESSENTIALS OF SYSTEMS ANALYSIS+DESIGN, Author: VALACICH, Publisher: PEARSON, Edition: 6TH 15, Price: 241.80 USD", "EBK ESSENTIALS OF SYSTEMS ANALYSIS AND, Author: VALACICH, Publisher: DGTL BNCOM, Edition: 6, Price: 98.99 USD", "EBK ESSENTIALS OF SYSTEMS ANALYSIS AND, Author: VALACICH, Publisher: DGTL BNCOM, Edition: 6, Price: 144.99 USD"], "isbns": ["9780133546231", "8220020246093", "9780133546361"], "title": "22503"}, {"status": ["Required", "Ebook Option", "Ebook Option"], "names": ["ESSENTIALS OF SYSTEMS ANALYSIS+DESIGN, Author: VALACICH, Publisher: PEARSON, Edition: 6TH 15, Price: 241.80 USD", "EBK ESSENTIALS OF SYSTEMS ANALYSIS AND, Author: VALACICH, Publisher: DGTL BNCOM, Edition: 6, Price: 98.99 USD", "EBK ESSENTIALS OF SYSTEMS ANALYSIS AND, Author: VALACICH, Publisher: DGTL BNCOM, Edition: 6, Price: 144.99 USD"], "isbns": ["9780133546231", "8220020246093", "9780133546361"], "title": "26732"}, {"status": ["Required", "Ebook Option", "Ebook Option"], "names": ["ESSENTIALS OF SYSTEMS ANALYSIS+DESIGN, Author: VALACICH, Publisher: PEARSON, Edition: 6TH 15, Price: 241.80 USD", "EBK ESSENTIALS OF SYSTEMS ANALYSIS AND, Author: VALACICH, Publisher: DGTL BNCOM, Edition: 6, Price: 98.99 USD", "EBK ESSENTIALS OF SYSTEMS ANALYSIS AND, Author: VALACICH, Publisher: DGTL BNCOM, Edition: 6, Price: 144.99 USD"], "isbns": ["9780133546231", "8220020246093", "9780133546361"], "title": "22504"}, {"status": ["Required", "Ebook Option", "Ebook Option"], "names": ["ESSENTIALS OF SYSTEMS ANALYSIS+DESIGN, Author: VALACICH, Publisher: PEARSON, Edition: 6TH 15, Price: 241.80 USD", "EBK ESSENTIALS OF SYSTEMS ANALYSIS AND, Author: VALACICH, Publisher: DGTL BNCOM, Edition: 6, Price: 98.99 USD", "EBK ESSENTIALS OF SYSTEMS ANALYSIS AND, Author: VALACICH, Publisher: DGTL BNCOM, Edition: 6, Price: 144.99 USD"], "isbns": ["9780133546231", "8220020246093", "9780133546361"], "title": "22505"}, {"status": ["Required"], "names": ["PROJECT MANAGEMENT, Author: KERZNER, Publisher: WILEY, Edition: 11TH 13, Price: 99.00 USD"], "isbns": ["9781118022276"], "title": "22700"}, {"status": ["Required"], "names": ["PROJECT MANAGEMENT, Author: KERZNER, Publisher: WILEY, Edition: 11TH 13, Price: 99.00 USD"], "isbns": ["9781118022276"], "title": "22702"}, {"status": ["Required", "Required", "Required", "Ebook Option"], "names": ["AGILE EXCELLENCE F/PRODUCT MANAGERS, Author: COHEN, Publisher: THINKAHA, Edition: 10, Price: 24.95 USD", "AGILE PRODUCT MANAGEMENT WITH SCRUM, Author: PICHLER, Publisher: PEARSON, Edition: 10, Price: 40.00 USD", "TAKE CHARGE PRODUCT MANAGEMENT, Author: GERACIE, Publisher: INGRAM, Edition: 13, Price: 32.95 USD", "EBK AGILE PRODUCT MANAGEMENT WITH SCRUM, Author: PICHLER, Publisher: DGTL BNCOM, Edition: 1, Price: 32.00 USD"], "isbns": ["9781607730743", "9780321605788", "9780983111627", "9780321684134"], "title": "26363"}, {"status": ["Required", "Required", "Required", "Ebook Option"], "names": ["AGILE EXCELLENCE F/PRODUCT MANAGERS, Author: COHEN, Publisher: THINKAHA, Edition: 10, Price: 24.95 USD", "AGILE PRODUCT MANAGEMENT WITH SCRUM, Author: PICHLER, Publisher: PEARSON, Edition: 10, Price: 40.00 USD", "TAKE CHARGE PRODUCT MANAGEMENT, Author: GERACIE, Publisher: INGRAM, Edition: 13, Price: 32.95 USD", "EBK AGILE PRODUCT MANAGEMENT WITH SCRUM, Author: PICHLER, Publisher: DGTL BNCOM, Edition: 1, Price: 32.00 USD"], "isbns": ["9781607730743", "9780321605788", "9780983111627", "9780321684134"], "title": "26364"}, {"status": ["Required"], "names": ["DATA MINING:CONCEPTS+TECHNIQUES, Author: HAN, Publisher: ELSEVIER, Edition: 3RD 12, Price: 74.95 USD"], "isbns": ["9780123814791"], "title": "22819"}, {"status": ["Required"], "names": ["DATA MINING:CONCEPTS+TECHNIQUES, Author: HAN, Publisher: ELSEVIER, Edition: 3RD 12, Price: 74.95 USD"], "isbns": ["9780123814791"], "title": "22820"}, {"status": ["Required", "Recommended"], "names": ["IT MANAGER'S HANDBOOK, Author: HOLTSNIDER, Publisher: ELSEVIER, Edition: 3RD 12, Price: 49.95 USD", "COURSEPACK IS 483: <HBS# 9-172-123>, Author: KUMAR, Publisher: XANEDU, Edition: W16"], "isbns": ["9780124159495", "2818440080432"], "title": "22815"}, {"status": ["Required", "Recommended"], "names": ["IT MANAGER'S HANDBOOK, Author: HOLTSNIDER, Publisher: ELSEVIER, Edition: 3RD 12, Price: 49.95 USD", "COURSEPACK IS 483: <HBS# 9-172-123>, Author: KUMAR, Publisher: XANEDU, Edition: W16"], "isbns": ["9780124159495", "2818440080432"], "title": "22816"}, {"status": ["Required", "Required", "Ebook Option", "Ebook Option"], "names": ["MASTERING REQUIREMENTS PROCESS, Author: ROBERTSON, Publisher: PEARSON, Edition: 3RD 13, Price: 70.00 USD", "SOFTWARE REQUIREMENTS, Author: WIEGERS, Publisher: PEARSON, Edition: 3RD 13, Price: 45.00 USD", "EBK MASTERING THE REQUIREMENTS PROCESS, Author: ROBERTSON, Publisher: DGTL BNCOM, Edition: 3, Price: 56.00 USD", "EBK SOFTWARE REQUIREMENTS, Author: WIEGERS, Publisher: DGTL BNCOM, Edition: 3, Price: 36.00 USD"], "isbns": ["9780321815743", "9780735679665", "9780132942843", "9780735679627"], "title": "22506"}, {"status": ["Required", "Required", "Ebook Option", "Ebook Option"], "names": ["MASTERING REQUIREMENTS PROCESS, Author: ROBERTSON, Publisher: PEARSON, Edition: 3RD 13, Price: 70.00 USD", "SOFTWARE REQUIREMENTS, Author: WIEGERS, Publisher: PEARSON, Edition: 3RD 13, Price: 45.00 USD", "EBK MASTERING THE REQUIREMENTS PROCESS, Author: ROBERTSON, Publisher: DGTL BNCOM, Edition: 3, Price: 56.00 USD", "EBK SOFTWARE REQUIREMENTS, Author: WIEGERS, Publisher: DGTL BNCOM, Edition: 3, Price: 36.00 USD"], "isbns": ["9780321815743", "9780735679665", "9780132942843", "9780735679627"], "title": "22507"}, {"status": [], "names": [], "isbns": [], "title": "22508"}, {"status": [], "names": [], "isbns": [], "title": "22509"}, {"status": [], "names": [], "isbns": [], "title": "22510"}, {"status": [], "names": [], "isbns": [], "title": "22511"}, {"status": [], "names": [], "isbns": [], "title": "22705"}, {"status": [], "names": [], "isbns": [], "title": "22706"}, {"status": ["Recommended"], "names": ["CLOUD AT YOUR SERVICE, Author: ROSENBERG, Publisher: INGRAM PUB, Edition: 11, Price: 30.00 USD"], "isbns": ["9781935182528"], "title": "26376"}, {"status": ["Recommended"], "names": ["CLOUD AT YOUR SERVICE, Author: ROSENBERG, Publisher: INGRAM PUB, Edition: 11, Price: 30.00 USD"], "isbns": ["9781935182528"], "title": "26377"}, {"status": ["Required", "Required"], "names": ["COURSEPACK IS 540<HBS>, Author: LEE, Publisher: XANEDU, Edition: W16", "GLOBAL SOFTWARE TEAMS, Author: CARMEL, Publisher: PEARSON, Edition: 99, Price: 80.00 USD"], "isbns": ["2818440080449", "9780139242182"], "title": "22817"}, {"status": ["Required", "Required"], "names": ["COURSEPACK IS 540<HBS>, Author: LEE, Publisher: XANEDU, Edition: W16", "GLOBAL SOFTWARE TEAMS, Author: CARMEL, Publisher: PEARSON, Edition: 99, Price: 80.00 USD"], "isbns": ["2818440080449", "9780139242182"], "title": "22818"}, {"status": ["Required", "Required", "Recommended"], "names": ["ICLICKER 2  REMOTE-W/REEF(6 MONTH) >BI<, Author: ICLICKER, Publisher: MAC HIGHER, Edition: 15, Price: 56.00 USD", "IT PROJECT PORTFOLIO MANAGEMENT-W/CD, Author: BONHAM, Publisher: ARTECH, Edition: 05, Price: 112.20 USD", "ADVANCED PROJECT PORTFOLIO MGMT..., Author: KENDALL, Publisher: J ROSS, Edition: 03, Price: 74.95 USD"], "isbns": ["9781498601634", "9781580537810", "9781932159028"], "title": "22709"}, {"status": ["Required", "Recommended"], "names": ["IT PROJECT PORTFOLIO MANAGEMENT-W/CD, Author: BONHAM, Publisher: ARTECH, Edition: 05, Price: 112.20 USD", "ADVANCED PROJECT PORTFOLIO MGMT..., Author: KENDALL, Publisher: J ROSS, Edition: 03, Price: 74.95 USD"], "isbns": ["9781580537810", "9781932159028"], "title": "22710"}, {"status": [], "names": [], "isbns": [], "title": "22512"}, {"status": [], "names": [], "isbns": [], "title": "22513"}, {"status": ["Required", "Required"], "names": ["CHANGE MANAGEMENT:PEOPLE SIDE OF CHANGE, Author: HIATT, Publisher: PROSCI, Edition: 03, Price: 22.75 USD", "ICLICKER 2  REMOTE-W/REEF(6 MONTH) >BI<, Author: ICLICKER, Publisher: MAC HIGHER, Edition: 15, Price: 56.00 USD"], "isbns": ["9781930885189", "9781498601634"], "title": "22713"}, {"status": ["Required"], "names": ["CHANGE MANAGEMENT:PEOPLE SIDE OF CHANGE, Author: HIATT, Publisher: PROSCI, Edition: 03, Price: 22.75 USD"], "isbns": ["9781930885189"], "title": "22714"}, {"status": ["Required"], "names": ["COURSEPACK IS 577 <HBS>, Author: FISHER, Publisher: XANEDU, Edition: W16"], "isbns": ["2818440080494"], "title": "22514"}, {"status": ["Required"], "names": ["COURSEPACK IS 577 <HBS>, Author: FISHER, Publisher: XANEDU, Edition: W16"], "isbns": ["2818440080494"], "title": "22515"}, {"status": [], "names": [], "isbns": [], "title": "27133"}, {"status": [], "names": [], "isbns": [], "title": "27134"}, {"status": ["Required", "Ebook Option"], "names": ["INFORMATION,TECHNOLOGY+INNOVATION, Author: JORDAN, Publisher: WILEY, Edition: 12, Price: 60.00 USD", "EBK INFORMATION, TECHNOLOGY, AND INNOVA, Author: JORDAN, Publisher: DGTL BNCOM, Edition: EDITION, Price: 60.00 USD"], "isbns": ["9781118155783", "9781118239308"], "title": "26711"}, {"status": ["Required", "Ebook Option"], "names": ["INFORMATION,TECHNOLOGY+INNOVATION, Author: JORDAN, Publisher: WILEY, Edition: 12, Price: 60.00 USD", "EBK INFORMATION, TECHNOLOGY, AND INNOVA, Author: JORDAN, Publisher: DGTL BNCOM, Edition: EDITION, Price: 60.00 USD"], "isbns": ["9781118155783", "9781118239308"], "title": "26712"}]